spfplus/__init__.py
spfplus-0.1.4.dist-info/DESCRIPTION.rst
spfplus-0.1.4.dist-info/METADATA
spfplus-0.1.4.dist-info/RECORD
spfplus-0.1.4.dist-info/WHEEL
spfplus-0.1.4.dist-info/metadata.json
spfplus-0.1.4.dist-info/top_level.txt
