Metadata-Version: 2.0
Name: spfplus
Version: 0.1.4
Summary: Sender Policy Framework (SPF) python library.
Home-page: https://github.com/theodorehu95/spfplus
Author: Hang Hu
Author-email: theodorehu95@gmail.com
License: MIT License
Download-URL: https://github.com/theodorehu95/spfplus/archive/{tag}.tar.gz
Keywords: spf,email,authentication
Platform: any
